jCompoundMapper_pywrapper/__init__.py
jCompoundMapper_pywrapper/jcompoundmapper.py
jCompoundMapper_pywrapper/utils.py
jCompoundMapper_pywrapper/jCompoundMapper/jCMapperCLI.jar
jCompoundMapper_pywrapper/jCompoundMapper/lgpl-2.1.txt
jcompoundmapper_pywrapper-0.0.3.dist-info/licenses/LICENSE
jcompoundmapper_pywrapper-0.0.3.dist-info/METADATA
jcompoundmapper_pywrapper-0.0.3.dist-info/WHEEL
jcompoundmapper_pywrapper-0.0.3.dist-info/top_level.txt
jcompoundmapper_pywrapper-0.0.3.dist-info/RECORD
