Metadata-Version: 2.4
Name: jcompoundmapper_pywrapper
Version: 0.0.3
Summary: Python wrapper for jCompoundMapper molecular fingerprints
Home-page: https://github.com/OlivierBeq/jcompoundmapper_pywrapper
Author: Olivier J. M. Béquignon
Author-email: "olivier.bequignon.maintainer@gmail.com"
Maintainer: Olivier J. M. Béquignon
Maintainer-email: "olivier.bequignon.maintainer@gmail.com"
Keywords: jCompoundMapper,molecular fingerprints,cheminformatics,toxicoinformatics,QSAR
Classifier: Development Status :: 5 - Production/Stable
Classifier: License :: OSI Approved :: MIT License
Classifier: Programming Language :: Python :: 3.10
Classifier: Programming Language :: Python :: 3.9
Classifier: Programming Language :: Python :: 3.8
Classifier: Programming Language :: Python :: 3.7
Classifier: Programming Language :: Python :: 3.6
License-File: LICENSE
Requires-Dist: more-itertools
Requires-Dist: numpy
Requires-Dist: pandas
Requires-Dist: rdkit
Requires-Dist: install-jdk==0.3.0
Requires-Dist: bounded-pool-executor==0.0.3
Requires-Dist: requests
Provides-Extra: docs
Requires-Dist: sphinx; extra == "docs"
Requires-Dist: sphinx-rtd-theme; extra == "docs"
Requires-Dist: sphinx-autodoc-typehints; extra == "docs"
Provides-Extra: testing
Requires-Dist: pytest; extra == "testing"
Dynamic: license-file
